CHANGES.txt
MANIFEST.in
README.txt
setup.py
js/__init__.py
js.fotorama.egg-info/PKG-INFO
js.fotorama.egg-info/SOURCES.txt
js.fotorama.egg-info/dependency_links.txt
js.fotorama.egg-info/entry_points.txt
js.fotorama.egg-info/namespace_packages.txt
js.fotorama.egg-info/not-zip-safe
js.fotorama.egg-info/requires.txt
js.fotorama.egg-info/top_level.txt
js/fotorama/__init__.py
js/fotorama/test_fotorama.txt
js/fotorama/resources/fotorama.css
js/fotorama/resources/fotorama.js
js/fotorama/resources/fotorama.png
js/fotorama/resources/fotorama@2x.png