Metadata-Version: 1.1
Name: js.fotorama
Version: 4.2.1
Summary: Fanstatic packaging of fotorama.js.
Home-page: https://bitbucket.org/it_spirit/js.fotorama
Author: Thomas Massmann
Author-email: thomas.massmann@it-spir.it
License: BSD
Download-URL: http://pypi.python.org/pypi/js.fotorama
Platform: UNKNOWN
